ngi_calculations/__init__.py
ngi_calculations/cpt_correlations/__init__.py
ngi_calculations/cpt_correlations/analysis.py
ngi_calculations/cpt_correlations/config.py
ngi_calculations/cpt_correlations/definitions/__init__.py
ngi_calculations/cpt_correlations/definitions/cpt_process.py
ngi_calculations/cpt_correlations/definitions/dev.py
ngi_calculations/cpt_correlations/definitions/geo.py
ngi_calculations/cpt_correlations/definitions/physics.py
ngi_calculations/cpt_correlations/definitions/soil.py
ngi_calculations/cpt_correlations/definitions/stats.py
ngi_calculations/cpt_correlations/definitions/types.py
ngi_calculations/cpt_correlations/definitions/vocabulary.py
ngi_calculations/cpt_correlations/main.py
ngi_calculations/cpt_correlations/methods/cpt_process/calculations.py
ngi_calculations/cpt_correlations/methods/cpt_process/options.py
ngi_calculations/cpt_correlations/models/cpt_cone.py
ngi_calculations/cpt_correlations/models/cpt_raw.py
ngi_calculations/cpt_correlations/models/geo.py
ngi_calculations/cpt_correlations/models/lab_data.py
ngi_calculations/cpt_correlations/utils/dataframes.py
ngi_calculations/cpt_correlations/utils/interpolation.py
ngi_calculations/cpt_correlations/utils/log.py
ngi_calculations/cpt_correlations/utils/models.py
ngi_calculations/cpt_correlations/utils/perf_log.py
ngi_calculations/cpt_correlations/utils/simplify.py
tests/__init__.py
tests/conftest.py
tests/data/__init__.py
tests/data/calculation_data.py
tests/data/calculations/testA.xlsx
tests/data/excel_data_column_mapping.py
tests/data/excel_import_model.py
tests/data/fake_analysis.py
tests/data/fake_data_utils.py
tests/data/faker_cpt.py
tests/data/import_from_excel.py
tests/methods/test_cpt_process.py
tests/methods/test_cpt_process_fake_data.py
tests/utils/test_dataframes.py
tests/utils/test_excel_import_utils.py
tests/utils/test_interpolation.py
ngi_calculations-0.1.10.dist-info/LICENSE
ngi_calculations-0.1.10.dist-info/METADATA
ngi_calculations-0.1.10.dist-info/WHEEL
ngi_calculations-0.1.10.dist-info/RECORD
